davidkhala/data/frame/pretty.py
davidkhala/data/frame/pandas/__init__.py
davidkhala_data_frame-0.1.0.dist-info/METADATA
davidkhala_data_frame-0.1.0.dist-info/WHEEL
davidkhala_data_frame-0.1.0.dist-info/RECORD
