Metadata-Version: 2.4
Name: davidkhala.data.frame
Version: 0.1.0
Author-email: David Liu <david-khala@hotmail.com>
Requires-Python: >=3.10
Provides-Extra: pandas
Requires-Dist: pandas; extra == 'pandas'
Provides-Extra: polars
Requires-Dist: polars; extra == 'polars'
Provides-Extra: pretty
Requires-Dist: tabulate; extra == 'pretty'
